AUTHORS.rst
CONTRIBUTING.rst
HISTORY.rst
LICENSE
MANIFEST.in
README.rst
setup.cfg
setup.py
docs/Makefile
docs/authors.rst
docs/conf.py
docs/contributing.rst
docs/history.rst
docs/index.rst
docs/installation.rst
docs/make.bat
docs/readme.rst
docs/usage.rst
libkg/__init__.py
libkg/cli.py
libkg/libkg.py
libkg/utils.py
libkg.egg-info/PKG-INFO
libkg.egg-info/SOURCES.txt
libkg.egg-info/dependency_links.txt
libkg.egg-info/entry_points.txt
libkg.egg-info/not-zip-safe
libkg.egg-info/requires.txt
libkg.egg-info/top_level.txt
libkg/build/__init__.py
libkg/build/thirdlibrarybuild.py
libkg/models/__init__.py
libkg/models/node.py
libkg/models/thirdlibrary.py
libkg/neo4j/__init__.py
libkg/neo4j/creator.py
libkg/neo4j/factory.py
libkg/neo4j/accessor/__init__.py
libkg/neo4j/accessor/base.py
libkg/neo4j/accessor/index.py
libkg/neo4j/accessor/label.py
libkg/neo4j/accessor/metadata.py
libkg/transfer/__init__.py
libkg/transfer/neo4j.py
libkg/util/__init__.py
libkg/util/path_util.py
tests/__init__.py
tests/test_libkg.py
tests/build/test_thirdlibrarybuild.py
tests/modles/__init__.py
tests/modles/test_thirdlibrary.py
tests/transfer/__init__.py
tests/transfer/test_neo4j.py